lspi/sample.py
lspi/domains.py
lspi/__init__.py
lspi/policy.py
lspi/solvers.py
lspi/basis_functions.py
lspi/lspi.py
lspi_python-1.0.1.dist-info/metadata.json
lspi_python-1.0.1.dist-info/METADATA
lspi_python-1.0.1.dist-info/WHEEL
lspi_python-1.0.1.dist-info/DESCRIPTION.rst
lspi_python-1.0.1.dist-info/top_level.txt
lspi_python-1.0.1.dist-info/RECORD
