Metadata-Version: 2.0
Name: lspi-python
Version: 1.0.1
Summary: LSPI algorithm in Python
Home-page: https://github.com/rhololkeolke/lspi-python
Author: Devin Schwab
Author-email: digidevin@gmail.com
License: BSD-3-Clause
Keywords: machinelearning ai
Platform: UNKNOWN
Classifier: Development Status :: 3 - Alpha
Classifier: Intended Audience :: Science/Research
Classifier: Topic :: Scientific/Engineering :: Artificial Intelligence
Classifier: License :: OSI Approved :: BSD License
Classifier: Programming Language :: Python :: 2.7
Requires-Dist: numpy
Requires-Dist: scipy
Provides-Extra: test
Requires-Dist: nosetests; extra == 'test'
Requires-Dist: coverage; extra == 'test'
